LICENSE
aiomsa/__init__.py
aiomsa/abc.py
aiomsa/exceptions.py
aiomsa/mock/__init__.py
aiomsa/mock/e2/__init__.py
aiomsa/mock/e2/static.py
aiomsa/py.typed
aiomsa/server.py
aiomsa/utils/record.py
aiomsa-0.1.0a8.dist-info/LICENSE
aiomsa-0.1.0a8.dist-info/WHEEL
aiomsa-0.1.0a8.dist-info/METADATA
aiomsa-0.1.0a8.dist-info/RECORD
