Metadata-Version: 2.1
Name: aiomsa
Version: 0.1.0a8
Summary: Asynchronous xApp framework
Home-page: https://github.com/facebookexternal/aiomsa
License: BSD-3-Clause
Keywords: xApp
Author: Facebook Connectivity
Requires-Python: >=3.7,<4.0
Classifier: Development Status :: 3 - Alpha
Classifier: Framework :: AsyncIO
Classifier: Intended Audience :: Telecommunications Industry
Classifier: License :: OSI Approved :: BSD License
Classifier: Programming Language :: Python
Classifier: Programming Language :: Python :: 3
Classifier: Programming Language :: Python :: 3.7
Classifier: Programming Language :: Python :: 3.8
Classifier: Programming Language :: Python :: 3.9
Classifier: Typing :: Typed
Provides-Extra: docs
Requires-Dist: aiohttp (>=3.5.4,<4.0.0)
Requires-Dist: aiohttp-swagger (>=1.0.9,<2.0.0)
Requires-Dist: furo (>=2021.2.21b25,<2022.0.0); extra == "docs"
Requires-Dist: prometheus-async (>=19.2.0,<20.0.0)
Requires-Dist: sphinx (>=3.4.3,<4.0.0); extra == "docs"
Requires-Dist: sphinx-autodoc-typehints (>=1.11.1,<2.0.0); extra == "docs"
Requires-Dist: sphinxcontrib-openapi (>=0.7.0,<0.8.0); extra == "docs"
Project-URL: Repository, https://github.com/facebookexternal/aiomsa
